odoo8_addon_l10n_it_sdi_channel-8.0.1.1.0.99.dev8-nspkg.pth
odoo_addons/l10n_it_sdi_channel/README.rst
odoo_addons/l10n_it_sdi_channel/__init__.py
odoo_addons/l10n_it_sdi_channel/__openerp__.py
odoo_addons/l10n_it_sdi_channel/i18n/it.po
odoo_addons/l10n_it_sdi_channel/i18n/l10n_it_sdi_channel.pot
odoo_addons/l10n_it_sdi_channel/models/__init__.py
odoo_addons/l10n_it_sdi_channel/models/company.py
odoo_addons/l10n_it_sdi_channel/models/fetchmail_server.py
odoo_addons/l10n_it_sdi_channel/models/ir_mail_server.py
odoo_addons/l10n_it_sdi_channel/models/sdi.py
odoo_addons/l10n_it_sdi_channel/readme/CONFIGURE.rst
odoo_addons/l10n_it_sdi_channel/readme/CONTRIBUTORS.rst
odoo_addons/l10n_it_sdi_channel/readme/DESCRIPTION.rst
odoo_addons/l10n_it_sdi_channel/security/ir.model.access.csv
odoo_addons/l10n_it_sdi_channel/security/security.xml
odoo_addons/l10n_it_sdi_channel/static/description/icon.png
odoo_addons/l10n_it_sdi_channel/static/description/index.html
odoo_addons/l10n_it_sdi_channel/views/company_view.xml
odoo_addons/l10n_it_sdi_channel/views/fetchmail_server.xml
odoo_addons/l10n_it_sdi_channel/views/ir_mail_server.xml
odoo_addons/l10n_it_sdi_channel/views/sdi_view.xml
odoo8_addon_l10n_it_sdi_channel-8.0.1.1.0.99.dev8.dist-info/METADATA
odoo8_addon_l10n_it_sdi_channel-8.0.1.1.0.99.dev8.dist-info/WHEEL
odoo8_addon_l10n_it_sdi_channel-8.0.1.1.0.99.dev8.dist-info/namespace_packages.txt
odoo8_addon_l10n_it_sdi_channel-8.0.1.1.0.99.dev8.dist-info/top_level.txt
odoo8_addon_l10n_it_sdi_channel-8.0.1.1.0.99.dev8.dist-info/RECORD
