Metadata-Version: 2.1
Name: odoo8-addon-l10n-it-sdi-channel
Version: 8.0.1.1.0.99.dev8
Summary: Aggiunge il canale di invio/ricezione dei file XML attraverso lo SdI
Home-page: https://github.com/OCA/l10n-italy
Author: Efatto.it di Sergio Corato, Odoo Community Association (OCA)
Author-email: support@odoo-community.org
License: AGPL-3
Platform: UNKNOWN
Classifier: Programming Language :: Python
Classifier: Framework :: Odoo
Classifier: License :: OSI Approved :: GNU Affero General Public License v3
Classifier: Development Status :: 3 - Alpha
Requires-Python: ~=2.7
Requires-Dist: odoo8-addon-l10n-it-fatturapa
Requires-Dist: odoo (<9.0a,>=8.0a)
